{
  "$schema": "https://schema.management.azure.com/schemas/2015-01-01/deploymentParameters.json#",
  "contentVersion": "1.0.0.0",
  "parameters": {
    "location": {
      "value": "westus3"
    },
    "networkInterfaceName1": {
      "value": "jhipster-vm20_z1"
    },
    "networkSecurityGroupName": {
      "value": "jhipster-vm-nsg"
    },
    "networkSecurityGroupRules": {
      "value": [
        {
          "name": "SSH",
          "properties": {
            "priority": 300,
            "protocol": "TCP",
            "access": "Allow",
            "direction": "Inbound",
            "sourceAddressPrefix": "*",
            "sourcePortRange": "*",
            "destinationAddressPrefix": "*",
            "destinationPortRange": "22"
          }
        },
        {
          "name": "HTTP-8080",
          "properties": {
            "priority": 310,
            "protocol": "TCP",
            "access": "Allow",
            "direction": "Inbound",
            "sourceAddressPrefix": "*",
            "sourcePortRange": "*",
            "destinationAddressPrefix": "*",
            "destinationPortRange": "8080"
          }
        }
      ]
    },
    "subnetName": {
      "value": "default"
    },
    "virtualNetworkName": {
      "value": "jhipster-vm-vnet"
    },
    "addressPrefixes": {
      "value": ["10.0.0.0/16"]
    },
    "subnets": {
      "value": [
        {
          "name": "default",
          "properties": {
            "addressPrefix": "10.0.0.0/24"
          }
        }
      ]
    },
    "publicIpAddressName1": {
      "value": "jhipster-vm-ip"
    },
    "publicIpAddressType": {
      "value": "Static"
    },
    "publicIpAddressSku": {
      "value": "Standard"
    },
    "pipDeleteOption": {
      "value": "Detach"
    },
    "virtualMachineName": {
      "value": "jhipster-vm"
    },
    "virtualMachineName1": {
      "value": "jhipster-vm"
    },
    "virtualMachineComputerName1": {
      "value": "jhipster-vm"
    },
    "virtualMachineRG": {
      "value": "jhipster-vm_group"
    },
    "osDiskType": {
      "value": "StandardSSD_LRS"
    },
    "osDiskDeleteOption": {
      "value": "Delete"
    },
    "virtualMachineSize": {
      "value": "Standard_B1s"
    },
    "nicDeleteOption": {
      "value": "Detach"
    },
    "hibernationEnabled": {
      "value": false
    },
    "adminUsername": {
      "value": "marufbek123"
    },
    "adminPassword": {
      "value": null
    },
    "enablePeriodicAssessment": {
      "value": "ImageDefault"
    },
    "securityType": {
      "value": "TrustedLaunch"
    },
    "secureBoot": {
      "value": true
    },
    "vTPM": {
      "value": true
    },
    "virtualMachine1Zone": {
      "value": "1"
    }
  }
}
